__init__.py
action.py
flow.py
meta.py
utils.py
py_daga-0.1.2.dist-info/licenses/LICENSE
py_daga-0.1.2.dist-info/METADATA
py_daga-0.1.2.dist-info/WHEEL
py_daga-0.1.2.dist-info/top_level.txt
py_daga-0.1.2.dist-info/RECORD
