Metadata-Version: 2.4
Name: py-daga
Version: 0.1.2
Summary: Py-Daga: Saga DAGs Made Easy
Author-email: River Studio <git@river-studio.net>
License:                                  Apache License
Classifier: License :: OSI Approved :: Apache Software License
Classifier: Programming Language :: Python :: 3.13
Requires-Python: >=3.13
License-File: LICENSE
Requires-Dist: networkx>=3.5
Dynamic: license-file
